chichitk/__init__.py
chichitk/aspect_frame.py
chichitk/buttons.py
chichitk/canvas_items.py
chichitk/collapse_frame.py
chichitk/dropdowns.py
chichitk/entry_boxes.py
chichitk/file_dialog.py
chichitk/function_progress.py
chichitk/icon_labels.py
chichitk/icons.py
chichitk/label_dropdown.py
chichitk/labels.py
chichitk/pdf_display.py
chichitk/player.py
chichitk/progress_bar.py
chichitk/scrollable_frame.py
chichitk/sliders.py
chichitk/temp_label.py
chichitk/temp_menu.py
chichitk/text_boxes.py
chichitk/timer.py
chichitk/tool_frame.py
chichitk/tool_tip.py
chichitk-0.0.6.dist-info/LICENSE
chichitk-0.0.6.dist-info/METADATA
chichitk-0.0.6.dist-info/WHEEL
chichitk-0.0.6.dist-info/top_level.txt
chichitk-0.0.6.dist-info/RECORD
