Metadata-Version: 2.1
Name: chichitk
Version: 0.0.6
Summary: Python UI library built upon Tkinter
Author-email: Samuel Gibson <samuelpgibson12@gmail.com>
License: MIT License
Project-URL: Homepage, https://github.com/SamGibson1/ChichiTk
Project-URL: Documentation, https://github.com/SamGibson1/ChichiTk/wiki
Project-URL: Bug Tracker, https://github.com/SamGibson1/ChichiTk/issues
Keywords: python,tkinter,custom,widgets
Classifier: Development Status :: 3 - Alpha
Classifier: Intended Audience :: Developers
Classifier: Programming Language :: Python :: 3
Classifier: License :: OSI Approved :: MIT License
Classifier: Operating System :: OS Independent
Requires-Python: >=3.7
License-File: LICENSE
Requires-Dist: opencv-python
Requires-Dist: numpy
Requires-Dist: Pillow
Requires-Dist: PyMuPDF
